{
	"bom":[
		{
			"PutRequest": {
				"Item": {
					"Name": {"S":"b'Howards End (2016 Restoration)'"},
					"Link": {"S":"http://www.boxofficemojo.com/movies/?id=howardsend2016.htm"},
					"ReleaseDate": {"S":"b'August 26, 2016'"},
					"Runtime": {"S":"b'2 hrs. 20 min.'"},
					"Distributor": {"S":"b'Cohen Media Group'"},
					"DomesticLifetimeGross": {"S":"b''"},
					"ProductionBudget": {"S":"b'N/A'"},
					"DomesticTotalasofSep.29,2016": {"S":"b'$160,282'"},
					"Genre": {"S":"b'Drama'"},
					"MPAARating": {"S":"b'PG'"},
					"Players": {"S":"b'No Player Information'"},
					"Domestic": {"S":"b'$26,126,837'"},
					"WidestRelease": {"S":"b'10 theaters'"},
					"OpeningWeekend": {"S":"b'$23,840'"},
					"InRelease": {"S":"b'35 days / 5 weeks'"},
					"Awards": {"S":"No Academy Awards Information"},
					"GenreRank": {"S":"No Genre Information"},
					"Franchise": {"S":"No Franchise Information"},
					"Chart": {"S":"{'Top Movies in the Past 365 Days': '342'}"}
				}
			}
		},
		{
			"PutRequest": {
				"Item": {
					"Name": {"S":"b'Howl'"},
					"Link": {"S":"http://www.boxofficemojo.com/movies/?id=howl.htm"},
					"ReleaseDate": {"S":"b'September 24, 2010'"},
					"Genre": {"S":"b'Drama'"},
					"Distributor": {"S":"b'Oscilloscope Pictures'"},
					"ProductionBudget": {"S":"b'N/A'"},
					"DomesticTotalGross": {"S":"b'$617,334'"},
					"Runtime": {"S":"b'1 hrs. 30 min.'"},
					"MPAARating": {"S":"b'R'"},
					"Producer": {"S":"b'Gus Van Sant'"},
					"Actor": {"S":"b'Jeff Daniels, James Franco, Jon Hamm, David Strathairn'"},
					"Domestic": {"S":"b'$617,334'"},
					"Worldwide": {"S":"b'$1,183,258'"},
					"Foreign": {"S":"b'$565,924'"},
					"WidestRelease": {"S":"b'29 theaters'"},
					"CloseDate": {"S":"b'February 10, 2011'"},
					"OpeningWeekend": {"S":"b'$51,185'"},
					"Awards": {"S":"No Academy Awards Information"},
					"GenreRank": {"S":"No Genre Information"},
					"Franchise": {"S":"No Franchise Information"},
					"Chart": {"S":"{'All Time Domestic': '7,959'}"}
				}
			}
		},
		{
			"PutRequest": {
				"Item": {
					"Name": {"S":"bHowl's Moving Castle"},
					"Link": {"S":"http://www.boxofficemojo.com/movies/?id=howlsmovingcastle.htm"},
					"ReleaseDate": {"S":"b'June 10, 2005'"},
					"Genre": {"S":"b'Animation'"},
					"Distributor": {"S":"b'Buena Vista'"},
					"ProductionBudget": {"S":"b'N/A'"},
					"DomesticTotalGross": {"S":"b'$4,711,096'"},
					"Runtime": {"S":"b'1 hrs. 59 min.'"},
					"MPAARating": {"S":"b'PG'"},
					"Producer": {"S":"b'John Lasseter'"},
					"Actor": {"S":"b'Christian Bale*, Billy Crystal*, Blythe Danner* , Jena Malone*, Emily Mortimer*'"},
					"Director": {"S":"b'Hayao Miyazaki'"},
					"Domestic": {"S":"b'$4,711,096'"},
					"Worldwide": {"S":"b'$235,184,110'"},
					"Foreign": {"S":"b'$230,473,014'"},
					"WidestRelease": {"S":"b'202 theaters'"},
					"CloseDate": {"S":"b'October 6, 2005'"},
					"OpeningWeekend": {"S":"b'$427,987'"},
					"InRelease": {"S":"b'119 days / 17 weeks'"},
					"Awards": {"S":"Nominated for One Oscar."},
					"GenreRank": {"S":"{'Animation - Fantasy': '51', 'Animation - Anime': '11', 'Animation': '247'}"},
					"Franchise": {"S":"{'Brand: Studio Ghibli': '4'}"},
					"Chart": {"S":"{'All Time Worldwide': '554', 'Yearly (Limited) 2005': '19', 'All Time Domestic': '5,462', 'Yearly 2005': '167', BOM Users' Grades (2005 Releases): '7', 'Yearly Opening Weekends (Limited) 2005': '21', 'Worldwide Yearly 2005': '15', 'Yearly Opening Weekends 2005': '159', 'Yearly PG Rated 2005': '31'}"}
				}
			}
		},
		{
			"PutRequest": {
				"Item": {
					"Name": {"S":"b'Hubble 3D'"},
					"Link": {"S":"http://www.boxofficemojo.com/movies/?id=hubble3d.htm"},
					"ReleaseDate": {"S":"b'March 19, 2010'"},
					"DomesticTotalasofMar.19,2017": {"S":"b'$51,806,692'"},
					"Distributor": {"S":"b'Warner Bros.'"},
					"ProductionBudget": {"S":"b'N/A'"},
					"Genre": {"S":"b'IMAX'"},
					"Runtime": {"S":"b'0 hrs. 43 min.'"},
					"MPAARating": {"S":"b'G'"},
					"Actor": {"S":"b'Leonardo DiCaprio*'"},
					"Domestic": {"S":"b'$51,806,692'"},
					"Worldwide": {"S":"b'$72,641,766'"},
					"Foreign": {"S":"b'$20,835,074'"},
					"WidestRelease": {"S":"b'151 theaters'"},
					"OpeningWeekend": {"S":"b'$413,477'"},
					"InRelease": {"S":"b'2,558 days / 365.4 weeks'"},
					"Awards": {"S":"No Academy Awards Information"},
					"GenreRank": {"S":"{'3D': '168'}"},
					"Franchise": {"S":"No Franchise Information"},
					"Chart": {"S":"{'Movies That Never Hit the Top 10 Adjusted': '8', 'Rated G': '82', 'All Time Domestic': '1,514', 'Movies That Never Hit the Top 5 Adjusted': '74', 'Movies That Never Hit the Top 5': '24', 'Rated G Adjusted': '130', 'Movies That Never Hit the Top 10': '5'}"}
				}
			}
		},
		{
			"PutRequest": {
				"Item": {
					"Name": {"S":"b'Hudson Hawk'"},
					"Link": {"S":"http://www.boxofficemojo.com/movies/?id=hudsonhawk.htm"},
					"ReleaseDate": {"S":"b'May 24, 1991'"},
					"Genre": {"S":"b'Action Comedy'"},
					"Distributor": {"S":"b'TriStar'"},
					"ProductionBudget": {"S":"b'$65 million'"},
					"DomesticTotalGross": {"S":"b'$17,218,080'"},
					"Runtime": {"S":"b'1 hrs. 35 min.'"},
					"MPAARating": {"S":"b'R'"},
					"Producer": {"S":"b'Joel Silver'"},
					"Actor": {"S":"b'Bruce Willis'"},
					"Cinematographer": {"S":"b'Dante Spinotti'"},
					"Writer": {"S":"b'Daniel Waters'"},
					"Composer": {"S":"b'Michael Kamen'"},
					"Director": {"S":"b'Michael Lehman'"},
					"Domestic": {"S":"b'$17,218,080'"},
					"WidestRelease": {"S":"b'2,072 theaters'"},
					"OpeningWeekend": {"S":"b'$7,082,820'"},
					"Awards": {"S":"No Academy Awards Information"},
					"GenreRank": {"S":"{'Heist / Caper': '53'}"},
					"Franchise": {"S":"No Franchise Information"},
					"Chart": {"S":"{'Yearly 1991': '70', BOM Users' Grades (1991 Releases): '69', 'Yearly Opening Weekends 1991': '31', 'All Time Domestic': '3,515', 'Highest All Time Rank (on July 2, 1991)': '814', 'Memorial Day 4-Day Holiday Weekends': '144', 'Memorial Day 4-Day Holiday Weekend Openers': '67', 'Yearly R Rated 1991': '34', 'Yearly Opening Weekends (Wide) 1991': '33', 'Yearly (Wide) 1991': '71'}"}
				}
			}
		},
		{
			"PutRequest": {
				"Item": {
					"Name": {"S":"b'Hugh Hefner: Playboy, Activist and Rebel'"},
					"Link": {"S":"http://www.boxofficemojo.com/movies/?id=hughhefner.htm"},
					"ReleaseDate": {"S":"b'July 30, 2010'"},
					"Genre": {"S":"b'Documentary'"},
					"Distributor": {"S":"b'Phase 4'"},
					"ProductionBudget": {"S":"b'N/A'"},
					"DomesticTotalGross": {"S":"b'$10,000'"},
					"Runtime": {"S":"b'2 hrs. 4 min.'"},
					"MPAARating": {"S":"b'R'"},
					"Players": {"S":"b'No Player Information'"},
					"Domestic": {"S":"b'$10,000'"},
					"WidestRelease": {"S":"b'4 theaters'"},
					"CloseDate": {"S":"b'August 5, 2010'"},
					"OpeningWeekend": {"S":"b'$10,000'"},
					"Awards": {"S":"No Academy Awards Information"},
					"GenreRank": {"S":"No Genre Information"},
					"Franchise": {"S":"No Franchise Information"},
					"Chart": {"S":"{'All Time Domestic': '13,353'}"}
				}
			}
		},
		{
			"PutRequest": {
				"Item": {
					"Name": {"S":"b'Hugo'"},
					"Link": {"S":"http://www.boxofficemojo.com/movies/?id=hugocabret.htm"},
					"ReleaseDate": {"S":"b'November 23, 2011'"},
					"Genre": {"S":"b'Family Adventure'"},
					"Distributor": {"S":"b'Paramount'"},
					"ProductionBudget": {"S":"b'N/A'"},
					"DomesticTotalGross": {"S":"b'$73,864,507'"},
					"Runtime": {"S":"b'2 hrs. 7 min.'"},
					"MPAARating": {"S":"b'PG'"},
					"Writer": {"S":"b'John Logan'"},
					"Producer": {"S":"b'Johnny Depp, Tim Headington, Graham King, Martin Scorsese'"},
					"Actor": {"S":"b'Ben Kingsley, Chloe Moretz, Sacha Baron Cohen, Jude Law, Emily Mortimer*, Christopher Lee*, Richard Griffiths*, Ray Winstone*'"},
					"Composer": {"S":"b'Howard Shore'"},
					"Director": {"S":"b'Martin Scorsese'"},
					"Domestic": {"S":"b'$73,864,507'"},
					"Worldwide": {"S":"b'$185,770,160'"},
					"Foreign": {"S":"b'$111,905,653'"},
					"WidestRelease": {"S":"b'2,608 theaters'"},
					"CloseDate": {"S":"b'April 12, 2012'"},
					"OpeningWeekend": {"S":"b'$11,364,505'"},
					"InRelease": {"S":"b'142 days / 20.3 weeks'"},
					"Awards": {"S":"Nominated for Eleven Oscars, Including Five Wins."},
					"GenreRank": {"S":"{'3D': '143', Family - Children's Book Adaptation: '40', 'Adventure - Period': '26', 'Young-Adult Book Adaptations': '31', 'Hollywood / Movies': '11', 'Travelogue - Paris': '10'}"},
					"Franchise": {"S":"{Showdown: 'Gravity' Vs. 'Life of Pi' Vs. 'Hugo': '3'}"},
					"Chart": {"S":"{'Thanksgiving 3-day Openings': '50', 'Thanksgiving 5-day Openings': '53', 'Opening Weeks Adjusted': '2,551', 'All Time Domestic': '983', 'Thanksgiving 3-day Openings Adjusted': '65', 'Twelfth Weekends Adjusted': '144', 'Thanksgiving 5-day Weekends': '104', 'Smallest Drops, All Wide Releases': '1,338', 'Opening Weekends - November': '176', 'Thanksgiving 5-day Weekends Adjusted': '121', 'Eleventh Weekends Adjusted': '142', 'Opening Weeks': '1,916', 'Thanksgiving 5-day Openings Adjusted': '66', 'Opening Weekends Adjusted': '2,292', 'Eleventh Weekends': '63', 'Thanksgiving 3-day Weekends': '117', 'Twelfth Weekends': '75', 'Tenth Weekends Adjusted': '189', 'Post-Thanksgiving Weekend - Best Holds': '18', 'Thanksgiving 3-day Weekends Adjusted': '155', 'Opening Weekends': '1,662', 'Best Picture Nomination Effect': '113', 'Tenth Weekends': '90'}"}
				}
			}
		},
		{
			"PutRequest": {
				"Item": {
					"Name": {"S":"b'Hugo Pool'"},
					"Link": {"S":"http://www.boxofficemojo.com/movies/?id=hugopool.htm"},
					"ReleaseDate": {"S":"b'December 12, 1997'"},
					"Genre": {"S":"b'Unknown'"},
					"Distributor": {"S":"b'Northern Arts'"},
					"ProductionBudget": {"S":"b'N/A'"},
					"DomesticTotalGross": {"S":"b'$13,330'"},
					"Runtime": {"S":"b'1 hrs. 34 min.'"},
					"MPAARating": {"S":"b'R'"},
					"Actor": {"S":"b'Sean Penn'"},
					"Domestic": {"S":"b'$13,330'"},
					"WidestRelease": {"S":"b'4 theaters'"},
					"CloseDate": {"S":"b'December 25, 1997'"},
					"OpeningWeekend": {"S":"b'$6,305'"},
					"InRelease": {"S":"b'14 days / 2 weeks'"},
					"Awards": {"S":"No Academy Awards Information"},
					"GenreRank": {"S":"No Genre Information"},
					"Franchise": {"S":"No Franchise Information"},
					"Chart": {"S":"{'Highest All Time Rank (on December 25, 1997)': '3984', 'Yearly Opening Weekends 1997': '250', 'All Time Domestic': '13,021', 'Yearly R Rated 1997': '157', 'Yearly Opening Weekends (Limited) 1997': '112', 'Yearly (Limited) 1997': '118', 'Yearly 1997': '293'}"}
				}
			}
		},
		{
			"PutRequest": {
				"Item": {
					"Name": {"S":"b'Hukkle'"},
					"Link": {"S":"http://www.boxofficemojo.com/movies/?id=hukkle.htm"},
					"ReleaseDate": {"S":"b'November 14, 2003'"},
					"Genre": {"S":"b'Unknown'"},
					"Distributor": {"S":"b'Shadow Dist.'"},
					"ProductionBudget": {"S":"b'N/A'"},
					"DomesticTotalGross": {"S":"b'$53,715'"},
					"Runtime": {"S":"b'1 hrs. 15 min.'"},
					"MPAARating": {"S":"b'Unrated'"},
					"Players": {"S":"b'No Player Information'"},
					"Domestic": {"S":"b'$53,715'"},
					"Worldwide": {"S":"b'$53,715'"},
					"Foreign": {"S":"b'n/a'"},
					"WidestRelease": {"S":"b'4 theaters'"},
					"CloseDate": {"S":"b'September 30, 2004'"},
					"InRelease": {"S":"b'301 days / 43 weeks'"},
					"Awards": {"S":"No Academy Awards Information"},
					"GenreRank": {"S":"{'Foreign Language': '1332'}"},
					"Franchise": {"S":"No Franchise Information"},
					"Chart": {"S":"{'Worldwide Yearly 2003': '307', 'All Time Domestic': '11,199', 'Yearly 2003': '386', 'Yearly (Limited) 2003': '240', 'Highest All Time Rank (on May 6, 2004)': '6003', 'Yearly Unrated Movies 2003': '87'}"}
				}
			}
		},
		{
			"PutRequest": {
				"Item": {
					"Name": {"S":"b'Hulk'"},
					"Link": {"S":"http://www.boxofficemojo.com/movies/?id=hulk.htm"},
					"ReleaseDate": {"S":"b'June 20, 2003'"},
					"Genre": {"S":"b'Action / Adventure'"},
					"Distributor": {"S":"b'Universal'"},
					"ProductionBudget": {"S":"b'$137 million'"},
					"DomesticTotalGross": {"S":"b'$132,177,234'"},
					"Runtime": {"S":"b'2 hrs. 15 min.'"},
					"MPAARating": {"S":"b'PG-13'"},
					"Writer": {"S":"b'Michael France, James Schamus'"},
					"Producer": {"S":"b'Avi Arad, Kevin Feige, Larry J. Franco, Gale Anne Hurd, Stan Lee'"},
					"Actor": {"S":"b'Eric Bana, Jennifer Connelly, Sam Elliott, Josh Lucas, Nick Nolte'"},
					"Composer": {"S":"b'Danny Elfman'"},
					"Director": {"S":"b'Ang Lee'"},
					"Domestic": {"S":"b'$132,177,234'"},
					"Worldwide": {"S":"b'$245,360,480'"},
					"Foreign": {"S":"b'$113,183,246'"},
					"WidestRelease": {"S":"b'3,674 theaters'"},
					"CloseDate": {"S":"b'October 16, 2003'"},
					"OpeningWeekend": {"S":"b'$62,128,420'"},
					"InRelease": {"S":"b'119 days / 17 weeks'"},
					"Awards": {"S":"No Academy Awards Information"},
					"GenreRank": {"S":"{'Sci-Fi Chase': '6', 'Superhero': '50', 'CGI Star': '23', 'Comic Book Adaptation': '50', 'Superhero - Origin': '24'}"},
					"Franchise": {"S":"{Showdown: 'Hulk' Vs. 'Hulk': '3', 'Showdown: Monster Mash: Kong vs. Hulk vs. Godzilla': '3', 'Brand: Marvel Comics': '32', 'Showdown: Marvel Mid-Range': '3'}"},
					"Chart": {"S":"{'Top 3-Day Grosses': '126', 'Biggest 2nd Weekend Drops': '96', 'Smallest Drops, 3,000+ theaters (Super-Saturation)': '890', 'Top 5-Day Grosses': '150', 'Opening Weekends - Summer': '79', BOM Users' Grades: '649', 'Worldwide Yearly 2003': '15', 'Opening Weeks Adjusted': '108', 'Single Day Saturday Gross': '178', 'Independence Day Weekends': '130', 'Highest All Time Rank (on September 21, 2003)': '149', 'Yearly Opening Weekends 2003': '6', 'Single Day Gross': '353', 'Smallest Drops, 2,000+ theaters (Very Wide)': '2,263', 'Yearly 2003': '14', 'All Time Worldwide': '521', 'Widest Opening Releases': '219', 'Single Day Friday Gross': '115', 'Widest PG-13 Rated Openings': '116', 'Opening Weekends Adjusted': '99', 'Yearly PG-13 Rated 2003': '7', 'Single Day Sunday Gross': '178', 'Smallest Drops, 2,500+ theaters (Saturation)': '1,626', 'Rated PG-13': '199', 'Widest PG-13 Rated Releases': '125', 'Widest Releases': '236', 'Rated PG-13 Adjusted': '190', 'Opening Weekends - June': '14', 'Opening Weekends': '131', 'Fastest to $100 million': '181', 'Rated PG-13, Opening Weekends': '87', 'All Time Domestic': '402', 'Single Day Sunday Gross Adjusted': '128', 'Smallest Drops, All Wide Releases': '4,329', 'Yearly Opening Weekends (Wide) 2003': '6', 'Theater Averages - Wide Opening Weekends': '147', 'Single Day Saturday Gross Adjusted': '136', 'Single Day Monday Gross Adjusted': '223', 'Opening Day Gross': '115', 'Opening Weeks': '148', 'Slowest to $100 million': '454', BOM Users' Grades (2003 Releases): '134', 'Opening Weekends Adjusted - Summer': '66', 'Single Day Friday Gross Adjusted': '78', 'Yearly (Wide) 2003': '15', 'Theater Averages - Wide Opening Weekends Adjusted': '145', 'Rated PG-13, Opening Weekends Adjusted': '71', 'Theater Averages (Wide Releases) - All Time': '163', 'Opening Weekends Adjusted - June': '13', 'Theater Averages (Wide Releases) - All Time Adjusted': '172', 'Top 7-Day Grosses': '158'}"}
				}
			}
		},
		{
			"PutRequest": {
				"Item": {
					"Name": {"S":"b'Hum Aapke Dil Mein Rahte Hain'"},
					"Link": {"S":"http://www.boxofficemojo.com/movies/?id=humaapkedilmeinrahtehain.htm"},
					"ReleaseDate": {"S":"b'N/A'"},
					"Genre": {"S":"b'Unknown'"},
					"Distributor": {"S":"b'Eros'"},
					"ProductionBudget": {"S":"b'N/A'"},
					"DomesticTotalGross": {"S":"b'$668,678'"},
					"Runtime": {"S":"b'N/A'"},
					"MPAARating": {"S":"b'Unrated'"},
					"Players": {"S":"b'No Player Information'"},
					"Domestic": {"S":"b'$668,678'"},
					"DomesticSummary": {"S":"b'No Domestic Summary Information'"},
					"Awards": {"S":"No Academy Awards Information"},
					"GenreRank": {"S":"No Genre Information"},
					"Franchise": {"S":"No Franchise Information"},
					"Chart": {"S":"{'All Time Domestic': '7,861'}"}
				}
			}
		},
		{
			"PutRequest": {
				"Item": {
					"Name": {"S":"b'Hum Saath-Saath Hain'"},
					"Link": {"S":"http://www.boxofficemojo.com/movies/?id=humsaathhain.htm"},
					"ReleaseDate": {"S":"b'November 5, 1999'"},
					"Genre": {"S":"b'Foreign'"},
					"Distributor": {"S":"b'Eros'"},
					"ProductionBudget": {"S":"b'N/A'"},
					"DomesticTotalGross": {"S":"b'$2,005,094'"},
					"Runtime": {"S":"b'2 hrs. 57 min.'"},
					"MPAARating": {"S":"b'Unrated'"},
					"Players": {"S":"b'No Player Information'"},
					"Domestic": {"S":"b'$2,005,094'"},
					"WidestRelease": {"S":"b'69 theaters'"},
					"OpeningWeekend": {"S":"b'$651,575'"},
					"InRelease": {"S":"b'52 days / 7.4 weeks'"},
					"Awards": {"S":"No Academy Awards Information"},
					"GenreRank": {"S":"No Genre Information"},
					"Franchise": {"S":"No Franchise Information"},
					"Chart": {"S":"{'Yearly Opening Weekends (Limited) 1999': '8', 'All Time Domestic': '6,505', 'Yearly (Limited) 1999': '44', 'Highest All Time Rank (on August 28, 2002)': '3058', 'Yearly Opening Weekends 1999': '140', 'Yearly 1999': '189'}"}
				}
			}
		},
		{
			"PutRequest": {
				"Item": {
					"Name": {"S":"b'Hum Tum'"},
					"Link": {"S":"http://www.boxofficemojo.com/movies/?id=humtum.htm"},
					"DomesticTotalasofJul.11,2004": {"S":"b'$796,641'"},
					"ReleaseDate": {"S":"b'May 28, 2004'"},
					"Genre": {"S":"b'Foreign'"},
					"Distributor": {"S":"b'Yash Raj'"},
					"ProductionBudget": {"S":"b'N/A'"},
					"Runtime": {"S":"b'2 hrs. 50 min.'"},
					"MPAARating": {"S":"b'Unrated'"},
					"Players": {"S":"b'No Player Information'"},
					"Domestic": {"S":"b'$796,641'"},
					"WidestRelease": {"S":"b'43 theaters'"},
					"OpeningWeekend": {"S":"b'$275,882'"},
					"InRelease": {"S":"b'45 days / 6.4 weeks'"},
					"Awards": {"S":"No Academy Awards Information"},
					"GenreRank": {"S":"{'Foreign Language': '476'}"},
					"Franchise": {"S":"No Franchise Information"},
					"Chart": {"S":"{'Yearly 2004': '231', 'Yearly (Limited) 2004': '79', 'All Time Domestic': '7,630', 'Highest All Time Rank (on July 8, 2004)': '4802', 'Yearly Opening Weekends 2004': '172', 'Yearly Opening Weekends (Limited) 2004': '34', 'Yearly Unrated Movies 2004': '19'}"}
				}
			}
		},
		{
			"PutRequest": {
				"Item": {
					"Name": {"S":"b'Hum to Mohabbt Karega'"},
					"Link": {"S":"http://www.boxofficemojo.com/movies/?id=humtomohabbtkarega.htm"},
					"ReleaseDate": {"S":"b'May 26, 2000'"},
					"Genre": {"S":"b'Unknown'"},
					"Distributor": {"S":"b'Eros'"},
					"ProductionBudget": {"S":"b'N/A'"},
					"DomesticTotalasofMay.29,2000": {"S":"b'$75,446'"},
					"Runtime": {"S":"b'N/A'"},
					"MPAARating": {"S":"b'Unrated'"},
					"Players": {"S":"b'No Player Information'"},
					"Domestic": {"S":"b'$75,446'"},
					"WidestRelease": {"S":"b'1 theaters'"},
					"OpeningWeekend": {"S":"b'$75,446'"},
					"InRelease": {"S":"b'4 days / 0.6 weeks'"},
					"Awards": {"S":"No Academy Awards Information"},
					"GenreRank": {"S":"No Genre Information"},
					"Franchise": {"S":"No Franchise Information"},
					"Chart": {"S":"{'Highest All Time Rank (on August 28, 2002)': '4262', 'All Time Domestic': '10,731', 'Yearly (Limited) 2000': '166', 'Yearly Opening Weekends 2000': '199', 'Yearly 2000': '316', 'Yearly Opening Weekends (Limited) 2000': '66'}"}
				}
			}
		},
		{
			"PutRequest": {
				"Item": {
					"Name": {"S":"b'Human Capital'"},
					"Link": {"S":"http://www.boxofficemojo.com/movies/?id=humancapital.htm"},
					"ReleaseDate": {"S":"b'January 9, 2015'"},
					"Genre": {"S":"b'Foreign'"},
					"Distributor": {"S":"b'Film Movement'"},
					"ProductionBudget": {"S":"b'N/A'"},
					"DomesticTotalGross": {"S":"b'$158,549'"},
					"Runtime": {"S":"b'1 hrs. 51 min.'"},
					"MPAARating": {"S":"b'Unrated'"},
					"Players": {"S":"b'No Player Information'"},
					"Domestic": {"S":"b'$158,549'"},
					"Worldwide": {"S":"b'$158,549'"},
					"Foreign": {"S":"b'n/a'"},
					"WidestRelease": {"S":"b'11 theaters'"},
					"CloseDate": {"S":"b'April 23, 2015'"},
					"InRelease": {"S":"b'105 days / 15 weeks'"},
					"Awards": {"S":"No Academy Awards Information"},
					"GenreRank": {"S":"{'Foreign Language': '983'}"},
					"Franchise": {"S":"No Franchise Information"},
					"Chart": {"S":"{'All Time Domestic': '9,714'}"}
				}
			}
		},
		{
			"PutRequest": {
				"Item": {
					"Name": {"S":"b'Human Centipede'"},
					"Link": {"S":"http://www.boxofficemojo.com/movies/?id=humancentipede.htm"},
					"ReleaseDate": {"S":"b'April 30, 2010'"},
					"Genre": {"S":"b'Horror'"},
					"Distributor": {"S":"b'IFC'"},
					"ProductionBudget": {"S":"b'N/A'"},
					"DomesticTotalGross": {"S":"b'$181,467'"},
					"Runtime": {"S":"b'1 hrs. 30 min.'"},
					"MPAARating": {"S":"b'R'"},
					"Players": {"S":"b'No Player Information'"},
					"Domestic": {"S":"b'$181,467'"},
					"Worldwide": {"S":"b'$252,207'"},
					"Foreign": {"S":"b'$70,740'"},
					"WidestRelease": {"S":"b'19 theaters'"},
					"CloseDate": {"S":"b'July 1, 2010'"},
					"OpeningWeekend": {"S":"b'$12,424'"},
					"InRelease": {"S":"b'63 days / 9 weeks'"},
					"Awards": {"S":"No Academy Awards Information"},
					"GenreRank": {"S":"No Genre Information"},
					"Franchise": {"S":"No Franchise Information"},
					"Chart": {"S":"{'All Time Domestic': '9,535'}"}
				}
			}
		},
		{
			"PutRequest": {
				"Item": {
					"Name": {"S":"b'Human Error'"},
					"Link": {"S":"http://www.boxofficemojo.com/movies/?id=humanerror.htm"},
					"ReleaseDate": {"S":"b'September 16, 2005'"},
					"Genre": {"S":"b'Fantasy Comedy'"},
					"Distributor": {"S":"b'New Deal Pictures'"},
					"ProductionBudget": {"S":"b'$1.5 million'"},
					"Runtime": {"S":"b'1 hrs. 35 min.'"},
					"MPAARating": {"S":"b'Unrated'"},
					"Players": {"S":"b'No Player Information'"},
					"TotalLifetimeGross": {"S":"b'No Total Lifetime Gross Information'"},
					"DomesticSummary": {"S":"b'No Domestic Summary Information'"},
					"Awards": {"S":"No Academy Awards Information"},
					"GenreRank": {"S":"No Genre Information"},
					"Franchise": {"S":"No Franchise Information"},
					"Chart": {"S":"No Chart Information"}
				}
			}
		},
		{
			"PutRequest": {
				"Item": {
					"Name": {"S":"b'Human Nature'"},
					"Link": {"S":"http://www.boxofficemojo.com/movies/?id=humannature.htm"},
					"ReleaseDate": {"S":"b'April 12, 2002'"},
					"Genre": {"S":"b'Comedy'"},
					"Distributor": {"S":"b'Fine Line'"},
					"ProductionBudget": {"S":"b'N/A'"},
					"DomesticTotalGross": {"S":"b'$705,308'"},
					"Runtime": {"S":"b'1 hrs. 36 min.'"},
					"MPAARating": {"S":"b'R'"},
					"Writer": {"S":"b'Charlie Kaufman'"},
					"Producer": {"S":"b'Ted Hope'"},
					"Actor": {"S":"b'Tim Robbins, Rhys Ifans, Hilary Duff*'"},
					"Composer": {"S":"b'Graeme Revell'"},
					"Director": {"S":"b'Michel Gondry'"},
					"Domestic": {"S":"b'$705,308'"},
					"Worldwide": {"S":"b'$705,308'"},
					"Foreign": {"S":"b'n/a'"},
					"WidestRelease": {"S":"b'224 theaters'"},
					"CloseDate": {"S":"b'May 9, 2002'"},
					"OpeningWeekend": {"S":"b'$297,340'"},
					"Awards": {"S":"No Academy Awards Information"},
					"GenreRank": {"S":"No Genre Information"},
					"Franchise": {"S":"No Franchise Information"},
					"Chart": {"S":"{'Highest All Time Rank (on August 28, 2002)': '3518', 'Yearly 2002': '244', 'Yearly (Limited) 2002': '85', 'All Time Domestic': '7,793', 'Worldwide Yearly 2002': '236', 'Yearly Opening Weekends 2002': '171', 'Yearly R Rated 2002': '103', 'Yearly Opening Weekends (Limited) 2002': '31'}"}
				}
			}
		},
		{
			"PutRequest": {
				"Item": {
					"Name": {"S":"b'Human Traffic'"},
					"Link": {"S":"http://www.boxofficemojo.com/movies/?id=humantraffic.htm"},
					"ReleaseDate": {"S":"b'May 5, 2000'"},
					"DomesticTotalasofMay.21,2000": {"S":"b'$104,257'"},
					"Distributor": {"S":"b'Miramax'"},
					"ProductionBudget": {"S":"b'N/A'"},
					"Genre": {"S":"b'Unknown'"},
					"Runtime": {"S":"b'1 hrs. 24 min.'"},
					"MPAARating": {"S":"b'R'"},
					"Players": {"S":"b'No Player Information'"},
					"Domestic": {"S":"b'$104,257'"},
					"WidestRelease": {"S":"b'22 theaters'"},
					"OpeningWeekend": {"S":"b'$26,160'"},
					"InRelease": {"S":"b'17 days / 2.4 weeks'"},
					"Awards": {"S":"No Academy Awards Information"},
					"GenreRank": {"S":"No Genre Information"},
					"Franchise": {"S":"No Franchise Information"},
					"Chart": {"S":"{'Highest All Time Rank (on August 28, 2002)': '4166', 'All Time Domestic': '10,304', 'Yearly R Rated 2000': '142', 'Yearly (Limited) 2000': '158', 'Yearly Opening Weekends 2000': '276', 'Yearly 2000': '306', 'Yearly Opening Weekends (Limited) 2000': '143'}"}
				}
			}
		},
		{
			"PutRequest": {
				"Item": {
					"Name": {"S":"b'Humanoids from the Deep'"},
					"Link": {"S":"http://www.boxofficemojo.com/movies/?id=humanoidsfromthedeep.htm"},
					"ReleaseDate": {"S":"b'1980'"},
					"Genre": {"S":"b'Unknown'"},
					"Distributor": {"S":"b'New World'"},
					"ProductionBudget": {"S":"b'N/A'"},
					"Runtime": {"S":"b'1 hrs. 20 min.'"},
					"MPAARating": {"S":"b'R'"},
					"Producer": {"S":"b'Hunt Lowry'"},
					"Composer": {"S":"b'James Horner'"},
					"TotalLifetimeGross": {"S":"b'No Total Lifetime Gross Information'"},
					"DomesticSummary": {"S":"b'No Domestic Summary Information'"},
					"Awards": {"S":"No Academy Awards Information"},
					"GenreRank": {"S":"No Genre Information"},
					"Franchise": {"S":"No Franchise Information"},
					"Chart": {"S":"No Chart Information"}
				}
			}
		},
		{
			"PutRequest": {
				"Item": {
					"Name": {"S":"b'Humans Vs. Zombies'"},
					"Link": {"S":"http://www.boxofficemojo.com/movies/?id=humansvszombies.htm"},
					"ReleaseDate": {"S":"b'November 11, 2011'"},
					"Genre": {"S":"b'Sci-Fi Horror'"},
					"Distributor": {"S":"b'Unknown'"},
					"ProductionBudget": {"S":"b'N/A'"},
					"Runtime": {"S":"b'1 hrs. 33 min.'"},
					"MPAARating": {"S":"b'Not Yet Rated'"},
					"Players": {"S":"b'No Player Information'"},
					"TotalLifetimeGross": {"S":"b'No Total Lifetime Gross Information'"},
					"DomesticSummary": {"S":"b'No Domestic Summary Information'"},
					"Awards": {"S":"No Academy Awards Information"},
					"GenreRank": {"S":"{'Sci-Fi Horror': '63', 'Zombie': '64'}"},
					"Franchise": {"S":"No Franchise Information"},
					"Chart": {"S":"No Chart Information"}
				}
			}
		},
		{
			"PutRequest": {
				"Item": {
					"Name": {"S":"b'Humble Pie'"},
					"Link": {"S":"http://www.boxofficemojo.com/movies/?id=humblepie.htm"},
					"ReleaseDate": {"S":"b'November 6, 2009'"},
					"Genre": {"S":"b'Comedy'"},
					"Distributor": {"S":"b'Monterey Media, Inc.'"},
					"ProductionBudget": {"S":"b'N/A'"},
					"DomesticTotalGross": {"S":"b'$3,359'"},
					"Runtime": {"S":"b'1 hrs. 24 min.'"},
					"MPAARating": {"S":"b'PG-13'"},
					"Actor": {"S":"b'William Baldwin, Kathleen Quinlan, Bruce McGill'"},
					"Domestic": {"S":"b'$3,359'"},
					"WidestRelease": {"S":"b'2 theaters'"},
					"CloseDate": {"S":"b'December 10, 2009'"},
					"OpeningWeekend": {"S":"b'$1,083'"},
					"InRelease": {"S":"b'35 days / 5 weeks'"},
					"Awards": {"S":"No Academy Awards Information"},
					"GenreRank": {"S":"No Genre Information"},
					"Franchise": {"S":"No Franchise Information"},
					"Chart": {"S":"{'All Time Domestic': '14,207', 'Yearly Opening Weekends 2009': '501', 'Yearly (Limited) 2009': '354', 'Yearly Opening Weekends (Limited) 2009': '362', 'Yearly PG-13 Rated 2009': '121', 'Yearly 2009': '506'}"}
				}
			}
		},
		{
			"PutRequest": {
				"Item": {
					"Name": {"S":"b'Humboldt County'"},
					"Link": {"S":"http://www.boxofficemojo.com/movies/?id=humboldtcounty.htm"},
					"ReleaseDate": {"S":"b'September 26, 2008'"},
					"Genre": {"S":"b'Comedy / Drama'"},
					"Distributor": {"S":"b'Magnolia'"},
					"ProductionBudget": {"S":"b'N/A'"},
					"DomesticTotalGross": {"S":"b'$82,357'"},
					"Runtime": {"S":"b'1 hrs. 37 min.'"},
					"MPAARating": {"S":"b'R'"},
					"Actor": {"S":"b'Fairuza Balk, Peter Bogdanovich, Chris Messina*'"},
					"Domestic": {"S":"b'$82,357'"},
					"WidestRelease": {"S":"b'9 theaters'"},
					"CloseDate": {"S":"b'November 6, 2008'"},
					"OpeningWeekend": {"S":"b'$25,933'"},
					"InRelease": {"S":"b'42 days / 6 weeks'"},
					"Awards": {"S":"No Academy Awards Information"},
					"GenreRank": {"S":"{'Slacker / Stoner': '59'}"},
					"Franchise": {"S":"No Franchise Information"},
					"Chart": {"S":"{'All Time Domestic': '10,618', 'Yearly (Limited) 2008': '204', 'Yearly R Rated 2008': '129', 'Yearly Opening Weekends 2008': '319', 'Yearly 2008': '377', 'Yearly Opening Weekends (Limited) 2008': '167'}"}
				}
			}
		},
		{
			"PutRequest": {
				"Item": {
					"Name": {"S":"b'Humko Deewana Kar Gaye'"},
					"Link": {"S":"http://www.boxofficemojo.com/movies/?id=humkodeewanakargaye.htm"},
					"ReleaseDate": {"S":"b'April 14, 2006'"},
					"Genre": {"S":"b'Foreign'"},
					"Distributor": {"S":"b'UTV Communications'"},
					"ProductionBudget": {"S":"b'N/A'"},
					"DomesticTotalGross": {"S":"b'$250,083'"},
					"Runtime": {"S":"b'2 hrs. 35 min.'"},
					"MPAARating": {"S":"b'Unrated'"},
					"Players": {"S":"b'No Player Information'"},
					"Domestic": {"S":"b'$250,083'"},
					"Worldwide": {"S":"b'$1,149,417'"},
					"Foreign": {"S":"b'$899,334'"},
					"WidestRelease": {"S":"b'39 theaters'"},
					"CloseDate": {"S":"b'May 14, 2006'"},
					"OpeningWeekend": {"S":"b'$108,630'"},
					"InRelease": {"S":"b'35 days / 5 weeks'"},
					"Awards": {"S":"No Academy Awards Information"},
					"GenreRank": {"S":"No Genre Information"},
					"Franchise": {"S":"No Franchise Information"},
					"Chart": {"S":"{'Yearly 2006': '311', 'Yearly Unrated Movies 2006': '34', 'Yearly Opening Weekends 2006': '230', 'Worldwide Yearly 2006': '299', 'All Time Domestic': '9,135', 'Yearly (Limited) 2006': '136', 'Yearly Opening Weekends (Limited) 2006': '72'}"}
				}
			}
		},
		{
			"PutRequest": {
				"Item": {
					"Name": {"S":"b'Humpday'"},
					"Link": {"S":"http://www.boxofficemojo.com/movies/?id=humpday.htm"},
					"ReleaseDate": {"S":"b'July 10, 2009'"},
					"Genre": {"S":"b'Comedy'"},
					"Distributor": {"S":"b'Magnolia'"},
					"ProductionBudget": {"S":"b'N/A'"},
					"DomesticTotalGross": {"S":"b'$407,377'"},
					"Runtime": {"S":"b'1 hrs. 33 min.'"},
					"MPAARating": {"S":"b'R'"},
					"Writer": {"S":"b'Lynn Shelton'"},
					"Producer": {"S":"b'Lynn Shelton'"},
					"Director": {"S":"b'Lynn Shelton'"},
					"Domestic": {"S":"b'$407,377'"},
					"Worldwide": {"S":"b'$473,980'"},
					"Foreign": {"S":"b'$66,603'"},
					"WidestRelease": {"S":"b'27 theaters'"},
					"CloseDate": {"S":"b'October 29, 2009'"},
					"OpeningWeekend": {"S":"b'$28,737'"},
					"InRelease": {"S":"b'112 days / 16 weeks'"},
					"Awards": {"S":"No Academy Awards Information"},
					"GenreRank": {"S":"No Genre Information"},
					"Franchise": {"S":"No Franchise Information"},
					"Chart": {"S":"{'Yearly R Rated 2009': '83', 'All Time Domestic': '8,463', 'Yearly Opening Weekends 2009': '276', 'Yearly (Limited) 2009': '93', 'Yearly Opening Weekends (Limited) 2009': '137', 'Yearly 2009': '244', 'Worldwide Yearly 2009': '286'}"}
				}
			}
		}
	]
}
